pdcast/__init__.py
pdcast/core.py
pdcast/types.py
pandas_downcast-1.2.4.dist-info/LICENSE
pandas_downcast-1.2.4.dist-info/METADATA
pandas_downcast-1.2.4.dist-info/WHEEL
pandas_downcast-1.2.4.dist-info/RECORD
