Metadata-Version: 2.1
Name: pandas-downcast
Version: 1.2.4
Summary: Shrink Pandas DataFrames with precision safe schema inference.
Home-page: https://github.com/domvwt/pandas-downcast
License: MIT
Author: Dominic Thorn
Author-email: dominic.thorn@gmail.com
Requires-Python: >=3.6.1,<4
Classifier: Intended Audience :: Developers
Classifier: License :: OSI Approved :: MIT License
Classifier: Programming Language :: Python :: 3
Classifier: Programming Language :: Python :: 3.7
Classifier: Programming Language :: Python :: 3.8
Classifier: Programming Language :: Python :: 3.9
Classifier: Programming Language :: Python :: 3.10
Classifier: Programming Language :: Python :: 3.11
Classifier: Programming Language :: Python :: 3.10
Classifier: Programming Language :: Python :: 3.6
Classifier: Programming Language :: Python :: 3.7
Classifier: Programming Language :: Python :: 3.8
Classifier: Programming Language :: Python :: 3.9
Requires-Dist: dataclasses ; python_version < "3.7"
Requires-Dist: numpy (>=1.16.5) ; python_version < "3.7"
Requires-Dist: numpy (>=1.17) ; python_version >= "3.7"
Requires-Dist: pandas (>=0.24)
Requires-Dist: typing-extensions ; python_version < "3.8"
Project-URL: Repository, https://github.com/domvwt/pandas-downcast
